opensprinkler-ha/__init__.py
opensprinkler_ha/__init__.py
opensprinkler_ha-0.19.dist-info/LICENSE
opensprinkler_ha-0.19.dist-info/METADATA
opensprinkler_ha-0.19.dist-info/WHEEL
opensprinkler_ha-0.19.dist-info/top_level.txt
opensprinkler_ha-0.19.dist-info/RECORD
