Metadata-Version: 2.1
Name: opensprinkler-ha
Version: 0.19
Summary: OpenSprinkler API for integration with Home Assistant
Home-page: https://github.com/philmottin
Author: Phil Mottin
Author-email: philmottin@gmail.com
License: UNKNOWN
Platform: UNKNOWN
Classifier: Programming Language :: Python :: 3
Classifier: License :: OSI Approved :: MIT License
Classifier: Operating System :: OS Independent
